util_itc/ITCcode.py
util_itc/__init__.py
util_itc-0.1.13.dist-info/LICENSE
util_itc-0.1.13.dist-info/METADATA
util_itc-0.1.13.dist-info/WHEEL
util_itc-0.1.13.dist-info/top_level.txt
util_itc-0.1.13.dist-info/RECORD
