Metadata-Version: 2.1
Name: util_itc
Version: 0.1.13
Summary: A package for fitting intertemporal choice data to models
Author-email: Chanyoung Chung <chanyoungchung@berkeley.edu>
Project-URL: Homepage, https://github.com/chany03/util_itc
Classifier: Programming Language :: Python :: 3
Classifier: License :: OSI Approved :: MIT License
Classifier: Operating System :: OS Independent
Requires-Python: >=3.8
License-File: LICENSE
Requires-Dist: numpy>=1.26.4
Requires-Dist: scipy>=1.12.0
